README.rst
setup.py
doc_x_to_html/__init__.py
doc_x_to_html/__main__.py
doc_x_to_html/doc_x_to_html.py
doc_x_to_html.egg-info/PKG-INFO
doc_x_to_html.egg-info/SOURCES.txt
doc_x_to_html.egg-info/dependency_links.txt
doc_x_to_html.egg-info/entry_points.txt
doc_x_to_html.egg-info/requires.txt
doc_x_to_html.egg-info/top_level.txt
test/test_cmdline.py