Metadata-Version: 1.2
Name: doc-x-to-html
Version: 0.0.2
Summary: Python command line application to convert multiple doc/docx files to html files.
Home-page: UNKNOWN
Author: Hugh Matsubara
Author-email: UNKNOWN
License: UNKNOWN
Platform: UNKNOWN
Requires-Python: >=3.0
